quantumgraphs/QGraph.py
quantumgraphs/QGraphList.py
quantumgraphs/__init__.py
quantumgraphs-0.1.10.dist-info/WHEEL
quantumgraphs-0.1.10.dist-info/METADATA
quantumgraphs-0.1.10.dist-info/RECORD
