Metadata-Version: 2.1
Name: quantumgraphs
Version: 0.1.10
Summary: Grow random graphs using quantum random walks
Author: ziofil
Author-email: miatto@gmail.com
Requires-Python: >=3.7,<4.0
Classifier: Programming Language :: Python :: 3
Classifier: Programming Language :: Python :: 3.7
Classifier: Programming Language :: Python :: 3.8
Requires-Dist: ipython (>=7.11,<8.0)
Requires-Dist: matplotlib (>=3.1,<4.0)
Requires-Dist: networkx (>=2.4,<3.0)
Requires-Dist: numpy (>=1.18,<2.0)
Requires-Dist: p-tqdm (>=1.3,<2.0)
Requires-Dist: pandas (>=0.25,<0.26)
Requires-Dist: scipy (>=1.4,<2.0)
Requires-Dist: seaborn (>=0.10,<0.11)
